<?xml version="1.0" encoding="UTF-8"?>
<beans xmlns="http://www.springframework.org/schema/beans"
	xmlns:xsi="http://www.w3.org/2001/XMLSchema-instance" xmlns:context="http://www.springframework.org/schema/context"
	xmlns:p="http://www.springframework.org/schema/p" xmlns:c="http://www.springframework.org/schema/c"
	xmlns:util="http://www.springframework.org/schema/util"
	xsi:schemaLocation="http://www.springframework.org/schema/beans http://www.springframework.org/schema/beans/spring-beans.xsd
	http://www.springframework.org/schema/context http://www.springframework.org/schema/context/spring-context.xsd">
	<context:annotation-config />
	<context:component-scan base-package="trading.app"></context:component-scan>
	
	<bean id="adapter" name="adapter, realTimeProvider" class="trading.app.adapter.plaza2.Plaza2Adapter"/>
	<bean id="historyProvider" class="trading.app.history.HibernateHistoryProvider"/>
	<bean  id="historyWriter" class="trading.app.history.HibernateHistoryWriter" init-method="init" >
		<property name="realTimeProvider" ref="realTimeProvider"></property>
	</bean>


	<bean id="tradingApplicationContext" class="trading.app.TradingApplicationContext">
		<property name="adapter" ref="adapter" />
		<property name="realTimeProvider" ref="realTimeProvider"/>
		<property name="historyProvider" ref="historyProvider" />
		<property name="historyWriter" ref="historyWriter" />
	</bean>
	<bean id="neuralContext" class="trading.app.neural.NeuralContext">
		<constructor-arg name="tradingApplicationContext" ref="tradingApplicationContext"></constructor-arg>
		<property name="neuralService" ref="neuralService"></property>
	</bean>
	
	<bean id="neuralService" class="trading.app.neural.NeuralService">
		<property name="neuralContext" ref="neuralContext"></property>
	</bean>

	
	<bean id="view" class="trading.view.swing.NeuralNetworkForm">
		<constructor-arg ref="neuralContext"></constructor-arg>
	</bean>
</beans>

